wheresyourtrash/__init__.py
wheresyourtrash/settings.py
wheresyourtrash/celery.py
wheresyourtrash/manage_wheresyourtrash.py
wheresyourtrash/urls.py
wheresyourtrash/wsgi.py
wheresyourtrash/apps/__init__.py
wheresyourtrash/apps/email2sms/__init__.py
wheresyourtrash/apps/email2sms/models.py
wheresyourtrash/apps/email2sms/urls.py
wheresyourtrash/apps/email2sms/serializers.py
wheresyourtrash/apps/email2sms/forms.py
wheresyourtrash/apps/email2sms/tests.py
wheresyourtrash/apps/email2sms/views.py
wheresyourtrash/apps/email2sms/api.py
wheresyourtrash/apps/email2sms/admin.py
wheresyourtrash/apps/email2sms/fixtures/initial_data.json
wheresyourtrash/apps/email2sms/migrations/__init__.py
wheresyourtrash/apps/email2sms/migrations/0002_load_initial_data.py
wheresyourtrash/apps/email2sms/migrations/0001_initial.py
wheresyourtrash/apps/email2sms/templates/base.html
wheresyourtrash/apps/email2sms/templates/email2sms/provider_list.html
wheresyourtrash/apps/email2sms/templates/email2sms/provider_form.html
wheresyourtrash/apps/email2sms/templates/email2sms/provider_detail.html
wheresyourtrash/apps/recurrent/__init__.py
wheresyourtrash/apps/recurrent/constants.py
wheresyourtrash/apps/recurrent/test.py
wheresyourtrash/apps/recurrent/event_parser.py
wheresyourtrash/apps/notifications/__init__.py
wheresyourtrash/apps/notifications/models.py
wheresyourtrash/apps/notifications/urls.py
wheresyourtrash/apps/notifications/serializers.py
wheresyourtrash/apps/notifications/forms.py
wheresyourtrash/apps/notifications/tasks.py
wheresyourtrash/apps/notifications/tests.py
wheresyourtrash/apps/notifications/managers.py
wheresyourtrash/apps/notifications/views.py
wheresyourtrash/apps/notifications/api.py
wheresyourtrash/apps/notifications/apps.py
wheresyourtrash/apps/notifications/admin.py
wheresyourtrash/apps/notifications/migrations/__init__.py
wheresyourtrash/apps/notifications/migrations/0001_initial.py
wheresyourtrash-3.4.0.dist-info/METADATA
wheresyourtrash-3.4.0.dist-info/entry_points.txt
wheresyourtrash-3.4.0.dist-info/metadata.json
wheresyourtrash-3.4.0.dist-info/DESCRIPTION.rst
wheresyourtrash-3.4.0.dist-info/RECORD
wheresyourtrash-3.4.0.dist-info/top_level.txt
wheresyourtrash-3.4.0.dist-info/WHEEL
