Metadata-Version: 2.0
Name: wheresyourtrash
Version: 3.4.0
Summary: A Django project for wheresyourtrash.com
Home-page: http://github.com/code4maine/wheresyourtrash
Author: Colin Powell
Author-email: colin.powell@gmail.com
License: BSD
Platform: OS Independent
Classifier: Development Status :: 4 - Beta
Classifier: Framework :: Django
Classifier: Intended Audience :: Developers
Classifier: License :: OSI Approved :: BSD License
Classifier: Operating System :: OS Independent
Classifier: Programming Language :: Python
Classifier: Topic :: Internet :: WWW/HTTP
Classifier: Topic :: Internet :: WWW/HTTP :: Dynamic Content
Requires-Dist: setuptools (>=18.0.1)
Requires-Dist: Django (>=1.9,<1.10)
Requires-Dist: django-configurations (>=1.0)
Requires-Dist: python-dateutil (>=2.5.2)
Requires-Dist: dj-database-url (>=0.3.0)
Requires-Dist: pylibmc (>=1.5.0)
Requires-Dist: Pillow (>=2.0.0)
Requires-Dist: django-cache-url (>=0.8.0)
Requires-Dist: werkzeug (>=0.9.4)
Requires-Dist: gunicorn (>=0.17.4)
Requires-Dist: easy-thumbnails (>=1.2)
Requires-Dist: whitenoise (>=3.2)
Requires-Dist: django-debug-toolbar (>=1.4)
Requires-Dist: django-extensions (>=1.6.1)
Requires-Dist: django-braces (>=1.4.0)
Requires-Dist: django-localflavor (>=1.1)
Requires-Dist: django-allauth (>=0.24.1)
Requires-Dist: django-floppyforms (>=1.6.1)
Requires-Dist: django-custom-user (>=0.6)
Requires-Dist: django-nose (>=1.4.1)
Requires-Dist: django-materializecss-form (>=1.0.1)
Requires-Dist: django-analytical (>=2.2)
Requires-Dist: raven (>=5.2.0)
Requires-Dist: factory-boy (>=2.5.1)
Requires-Dist: boto (>=2.39.0)
Requires-Dist: celery[redis] (>=3.1.23)
Requires-Dist: django-storages (>=1.1.8)
Requires-Dist: djangorestframework (>=3.3.2)
Requires-Dist: django-cors-headers (>=1.1.0)
Requires-Dist: markdown (>=2.6.1)
Requires-Dist: django-filter (>=0.9.2)
Requires-Dist: django-templated-email (>=0.4.9)
Requires-Dist: psycopg2 (>=2.5)
Requires-Dist: parsedatetime (>=2.1)
Requires-Dist: django-crispy-forms
